bible/__init__.py
bible/api.py
bible/citations.py
bible/database.py
bible/reader.py
bible/assets/bible.csv
bible_core-0.1.0.dist-info/LICENSE
bible_core-0.1.0.dist-info/METADATA
bible_core-0.1.0.dist-info/WHEEL
bible_core-0.1.0.dist-info/top_level.txt
bible_core-0.1.0.dist-info/RECORD
